swish_package/__init__.py
swish_activation-0.0.1.dist-info/LICENSE.txt
swish_activation-0.0.1.dist-info/METADATA
swish_activation-0.0.1.dist-info/WHEEL
swish_activation-0.0.1.dist-info/top_level.txt
swish_activation-0.0.1.dist-info/RECORD
