Metadata-Version: 2.1
Name: swish-activation
Version: 0.0.1
Summary: swish activation function
Home-page: https://github.com/Sagu12
Author: Sagnik Banerjee
Author-email: sagu7065@gmail.com
License: UNKNOWN
Platform: UNKNOWN
Classifier: Programming Language :: Python :: 3
Classifier: License :: OSI Approved :: MIT License
Classifier: Operating System :: OS Independent
